odoo/addons/account_payment_fr_lcr/README.rst
odoo/addons/account_payment_fr_lcr/__init__.py
odoo/addons/account_payment_fr_lcr/__manifest__.py
odoo/addons/account_payment_fr_lcr/post_install.py
odoo/addons/account_payment_fr_lcr/data/account_payment_method.xml
odoo/addons/account_payment_fr_lcr/i18n/account_banking_fr_lcr.pot
odoo/addons/account_payment_fr_lcr/i18n/account_payment_fr_lcr.pot
odoo/addons/account_payment_fr_lcr/i18n/es.po
odoo/addons/account_payment_fr_lcr/i18n/fr.po
odoo/addons/account_payment_fr_lcr/i18n/nb_NO.po
odoo/addons/account_payment_fr_lcr/models/__init__.py
odoo/addons/account_payment_fr_lcr/models/account_move.py
odoo/addons/account_payment_fr_lcr/models/account_payment.py
odoo/addons/account_payment_fr_lcr/models/account_payment_line.py
odoo/addons/account_payment_fr_lcr/models/account_payment_method.py
odoo/addons/account_payment_fr_lcr/models/account_payment_method_line.py
odoo/addons/account_payment_fr_lcr/models/account_payment_order.py
odoo/addons/account_payment_fr_lcr/models/res_partner_bank.py
odoo/addons/account_payment_fr_lcr/readme/CONFIGURE.md
odoo/addons/account_payment_fr_lcr/readme/CONTRIBUTORS.md
odoo/addons/account_payment_fr_lcr/readme/DESCRIPTION.md
odoo/addons/account_payment_fr_lcr/readme/INSTALL.md
odoo/addons/account_payment_fr_lcr/readme/USAGE.md
odoo/addons/account_payment_fr_lcr/reports/lettre_de_change.pdf
odoo/addons/account_payment_fr_lcr/static/description/icon.png
odoo/addons/account_payment_fr_lcr/static/description/index.html
odoo/addons/account_payment_fr_lcr/tests/__init__.py
odoo/addons/account_payment_fr_lcr/tests/test_fr_lcr.py
odoo/addons/account_payment_fr_lcr/views/account_move.xml
odoo/addons/account_payment_fr_lcr/views/account_payment_method_line.xml
odoo/addons/account_payment_fr_lcr/views/account_payment_order.xml
odoo_addon_account_payment_fr_lcr-19.0.1.1.0.dist-info/METADATA
odoo_addon_account_payment_fr_lcr-19.0.1.1.0.dist-info/WHEEL
odoo_addon_account_payment_fr_lcr-19.0.1.1.0.dist-info/top_level.txt
odoo_addon_account_payment_fr_lcr-19.0.1.1.0.dist-info/RECORD
