Metadata-Version: 2.1
Name: odoo-addon-account_payment_fr_lcr
Version: 19.0.1.1.0
Requires-Dist: odoo-addon-account_payment_batch_oca==19.0.*
Requires-Dist: odoo==19.0.*
Requires-Dist: pypdf>=3.1.0
Requires-Dist: unidecode
Summary: Create French LCR CFONB files
Home-page: https://github.com/OCA/l10n-france
License: AGPL-3
Author: Akretion,Odoo Community Association (OCA)
Author-email: support@odoo-community.org
Classifier: Programming Language :: Python
Classifier: Framework :: Odoo
Classifier: Framework :: Odoo :: 19.0
Classifier: License :: OSI Approved :: GNU Affero General Public License v3
